COPYING
COPYING.lesser
MANIFEST.in
NOTICE
README.md
requirements.txt
setup.py
compiler/__init__.py
compiler/api/__init__.py
compiler/api/compiler.py
compiler/api/source/auth_key.tl
compiler/api/source/main_api.tl
compiler/api/source/sys_msgs.tl
compiler/api/template/combinator.txt
compiler/api/template/type.txt
compiler/docs/__init__.py
compiler/docs/compiler.py
compiler/docs/template/page.txt
compiler/docs/template/toctree.txt
compiler/errors/__init__.py
compiler/errors/compiler.py
compiler/errors/sort.py
compiler/errors/source/303_SEE_OTHER.tsv
compiler/errors/source/400_BAD_REQUEST.tsv
compiler/errors/source/401_UNAUTHORIZED.tsv
compiler/errors/source/403_FORBIDDEN.tsv
compiler/errors/source/406_NOT_ACCEPTABLE.tsv
compiler/errors/source/420_FLOOD.tsv
compiler/errors/source/500_INTERNAL_SERVER_ERROR.tsv
compiler/errors/source/503_SERVICE_UNAVAILABLE.tsv
compiler/errors/template/class.txt
compiler/errors/template/sub_class.txt
tegram/__init__.py
tegram/client.py
tegram/dispatcher.py
tegram/emoji.py
tegram/file_id.py
tegram/filters.py
tegram/mime_types.py
tegram/py.typed
tegram/sync.py
tegram/utils.py
tegram.egg-info/PKG-INFO
tegram.egg-info/SOURCES.txt
tegram.egg-info/dependency_links.txt
tegram.egg-info/not-zip-safe
tegram.egg-info/requires.txt
tegram.egg-info/top_level.txt
tegram/connection/__init__.py
tegram/connection/connection.py
tegram/connection/transport/__init__.py
tegram/connection/transport/tcp/__init__.py
tegram/connection/transport/tcp/tcp.py
tegram/connection/transport/tcp/tcp_abridged.py
tegram/connection/transport/tcp/tcp_abridged_o.py
tegram/connection/transport/tcp/tcp_full.py
tegram/connection/transport/tcp/tcp_intermediate.py
tegram/connection/transport/tcp/tcp_intermediate_o.py
tegram/crypto/__init__.py
tegram/crypto/aes.py
tegram/crypto/mtproto.py
tegram/crypto/prime.py
tegram/crypto/rsa.py
tegram/enums/__init__.py
tegram/enums/auto_name.py
tegram/enums/chat_action.py
tegram/enums/chat_event_action.py
tegram/enums/chat_member_status.py
tegram/enums/chat_members_filter.py
tegram/enums/chat_type.py
tegram/enums/message_entity_type.py
tegram/enums/message_media_type.py
tegram/enums/message_service_type.py
